src/__init__.py
src/add_contact.ui
src/client.py
src/client_database.py
src/client_db.sqlite3
src/client_gui_settings.py
src/config.py
src/decorators.py
src/del_contact.ui
src/descriptors.py
src/main_window.py
src/main_window.ui
src/meta.py
src/test_client.py
src/logs/__init__.py
src/logs/config/__init__.py
src/logs/config/client_config_log.py
quickim-0.2.1.dist-info/METADATA
quickim-0.2.1.dist-info/WHEEL
quickim-0.2.1.dist-info/top_level.txt
quickim-0.2.1.dist-info/RECORD
