Metadata-Version: 2.1
Name: quickim
Version: 0.2.1
Summary: QuickIM client application
Home-page: https://github.com/Simper007/quickIM
Author: Artem Naumov
Author-email: simperu@yandex.ru
License: UNKNOWN
Platform: UNKNOWN
Requires-Python: >=3.5
Requires-Dist: PyQt5 (>=5.9)
Requires-Dist: SQLAlchemy (>=1.1.15)
